LICENSE
README.md
setup.cfg
setup.py
RupineHeroku/__init__.py
RupineHeroku/DataStructures/ObjEvmTokenHistory.py
RupineHeroku/DataStructures/ObjViewEvmTokenHistory.py
RupineHeroku/DataStructures/__init__.py
RupineHeroku/rupine_db/__init__.py
RupineHeroku/rupine_db/herokuAbi.py
RupineHeroku/rupine_db/herokuCredentials.py
RupineHeroku/rupine_db/herokuDFI.py
RupineHeroku/rupine_db/herokuDWH.py
RupineHeroku/rupine_db/herokuDXS.py
RupineHeroku/rupine_db/herokuDbAccess.py
RupineHeroku/rupine_db/herokuDbDML.py
RupineHeroku/rupine_db/herokuDwhNetwork.py
RupineHeroku/rupine_db/herokuDwhNetworkStatisticHistory.py
RupineHeroku/rupine_db/herokuEvmLiquidityPools.py
RupineHeroku/rupine_db/herokuEvmLiquidityPoolsHistory.py
RupineHeroku/rupine_db/herokuKeywordConfig.py
RupineHeroku/rupine_db/herokuTax.py
RupineHeroku/rupine_db/herokuToken.py
RupineHeroku/rupine_db/herokuTokenHistory.py
RupineHeroku/rupine_db/herokuViewTokenLatest.py
RupineHeroku/rupine_db/test.py
RupineHeroku/rupine_db/v_evm_latest_token_liquidity_pools.py
rupineHeroku.egg-info/PKG-INFO
rupineHeroku.egg-info/SOURCES.txt
rupineHeroku.egg-info/dependency_links.txt
rupineHeroku.egg-info/requires.txt
rupineHeroku.egg-info/top_level.txt